CHANGELOG.txt
LICENSE.txt
MANIFEST.in
README.txt
setup.py
ClintonPytorchTrainer/__init__.py
ClintonPytorchTrainer/core.py
ClintonPytorchTrainer.egg-info/PKG-INFO
ClintonPytorchTrainer.egg-info/SOURCES.txt
ClintonPytorchTrainer.egg-info/dependency_links.txt
ClintonPytorchTrainer.egg-info/top_level.txt