Metadata-Version: 2.1
Name: ClintonPytorchTrainer
Version: 0.0.3
Summary: PyTorch Trainer Class
Home-page: 
Author: Clinton Nyaore
Author-email: cnyaore@gmail.com
License: MIT
Keywords: pytorch
Classifier: Development Status :: 5 - Production/Stable
Classifier: Intended Audience :: Education
Classifier: Operating System :: Microsoft :: Windows :: Windows 10
Classifier: License :: OSI Approved :: MIT License
Classifier: Programming Language :: Python :: 3
License-File: LICENSE.txt
